LICENSE.BAYKIT
README.md
setup.py
bayserver_docker_fcgi/__init__.py
bayserver_docker_fcgi/fcg_command.py
bayserver_docker_fcgi/fcg_command_handler.py
bayserver_docker_fcgi/fcg_command_unpacker.py
bayserver_docker_fcgi/fcg_docker.py
bayserver_docker_fcgi/fcg_handler.py
bayserver_docker_fcgi/fcg_inbount_handler.py
bayserver_docker_fcgi/fcg_packet.py
bayserver_docker_fcgi/fcg_packet_factory.py
bayserver_docker_fcgi/fcg_packet_unpacker.py
bayserver_docker_fcgi/fcg_params.py
bayserver_docker_fcgi/fcg_port_docker.py
bayserver_docker_fcgi/fcg_protocol_handler.py
bayserver_docker_fcgi/fcg_type.py
bayserver_docker_fcgi/fcg_warp_docker.py
bayserver_docker_fcgi/fcg_warp_handler.py
bayserver_docker_fcgi.egg-info/PKG-INFO
bayserver_docker_fcgi.egg-info/SOURCES.txt
bayserver_docker_fcgi.egg-info/dependency_links.txt
bayserver_docker_fcgi.egg-info/requires.txt
bayserver_docker_fcgi.egg-info/top_level.txt
bayserver_docker_fcgi/command/__init__.py
bayserver_docker_fcgi/command/cmd_begin_request.py
bayserver_docker_fcgi/command/cmd_end_request.py
bayserver_docker_fcgi/command/cmd_params.py
bayserver_docker_fcgi/command/cmd_stderr.py
bayserver_docker_fcgi/command/cmd_stdin.py
bayserver_docker_fcgi/command/cmd_stdout.py
bayserver_docker_fcgi/command/in_out_command_base.py